api/__init__.py
api/main_api.py
api/query_handler.py
api/routes.py
intent_classifier/__init__.py
intent_classifier/intent_predictor.py
intent_classifier/intent_router.py
isro_helpbot/__init__.py
isro_helpbot/cli.py
isro_helpbot/config.py
isro_helpbot/core/__init__.py
isro_helpbot/core/chat_engine.py
isro_helpbot-1.0.0.dist-info/licenses/LICENSE
kg_builder/__init__.py
kg_builder/build_kg.py
kg_builder/docx_pdf_parser.py
kg_builder/entity_extractor.py
kg_builder/geospatial_extractor.py
kg_builder/relationship_mapper.py
kg_builder/response_generator.py
kg_builder/text_preprocessor.py
ui/__init__.py
ui/streamlit_app.py
ui/static/gaurav.jpg
ui/static/jatin.jpg
ui/static/kg_graph.html
ui/static/moon_bg.png
ui/static/pratyay.jpg
ui/static/saksham.jpg
ui/templates/index.html
isro_helpbot-1.0.0.dist-info/METADATA
isro_helpbot-1.0.0.dist-info/WHEEL
isro_helpbot-1.0.0.dist-info/entry_points.txt
isro_helpbot-1.0.0.dist-info/top_level.txt
isro_helpbot-1.0.0.dist-info/RECORD
