Metadata-Version: 2.4
Name: isro-helpbot
Version: 1.0.0
Summary: AI-based Help Bot for Information Retrieval from MOSDAC using a Knowledge Graph
Author: Your Name
Author-email: Your Name <your.email@example.com>
License: MIT License
Classifier: Programming Language :: Python :: 3
Classifier: Framework :: FastAPI
Classifier: Intended Audience :: Developers
Classifier: Operating System :: OS Independent
Requires-Python: >=3.7
License-File: LICENSE
Requires-Dist: requests
Requires-Dist: beautifulsoup4
Requires-Dist: pandas
Requires-Dist: nltk
Requires-Dist: spacy==3.7.2
Requires-Dist: networkx
Requires-Dist: sentence-transformers
Requires-Dist: streamlit
Requires-Dist: python-docx
Requires-Dist: pymupdf
Requires-Dist: selenium
Requires-Dist: webdriver-manager
Requires-Dist: langchain
Requires-Dist: openai==0.28
Requires-Dist: PyPDF2
Requires-Dist: fastapi
Requires-Dist: uvicorn
Requires-Dist: faiss-cpu
Requires-Dist: matplotlib
Requires-Dist: pyvis
Requires-Dist: scikit-learn
Requires-Dist: openpyxl
Dynamic: author
Dynamic: license-file
Dynamic: requires-python
